[
  {
    "id": "advantage-and-disadvantage",
    "name": "Advantage and Disadvantage",
    "tag": "Condition",
    "summary": "Tira dos d20 y toma el mejor o el peor.",
    "text": "Con ventaja tiras 2d20 y tomas el mayor; con desventaja, el menor.",
    "seeAlso": ["attack-rolls", "ability-checks"]
  },
  {
    "id": "area-of-effect-cone",
    "name": "Areas: Cone",
    "tag": "Area of Effect",
    "summary": "Área cónica desde un punto de origen.",
    "text": "Los conos cubren una región en expansión desde el origen; el DM determina cobertura exacta en el mapa."
  },
  {
    "id": "grappled",
    "name": "Grappled",
    "tag": "Condition",
    "summary": "Tu velocidad pasa a 0.",
    "text": "La condición termina si el agarrador queda incapacitado o te alejas de su alcance.",
    "seeAlso": ["escape-grapple"]
  },
  {
    "id": "attitude",
    "name": "Attitude",
    "tag": "Attitude",
    "summary": "Hostil, Indiferente, Amistoso.",
    "text": "La actitud base guía la dificultad de la interacción social.",
    "seeAlso": ["influence"]
  }
]
